wealthbox/__init__.py
wealthbox-0.8.0.dist-info/METADATA
wealthbox-0.8.0.dist-info/WHEEL
wealthbox-0.8.0.dist-info/RECORD
