Metadata-Version: 2.4
Name: wealthbox
Version: 0.8.0
Summary: 
Author: spencerogden-dsam
Author-email: 67068943+spencerogden-dsam@users.noreply.github.com
Requires-Python: >=3.9,<4.0
Classifier: Programming Language :: Python :: 3
Classifier: Programming Language :: Python :: 3.9
Classifier: Programming Language :: Python :: 3.10
Classifier: Programming Language :: Python :: 3.11
Classifier: Programming Language :: Python :: 3.12
Classifier: Programming Language :: Python :: 3.13
Classifier: Programming Language :: Python :: 3.14
Requires-Dist: requests (>=2.27.1,<3.0.0)
